[ {
  "name" : "Alice",
  "age" : 25,
  "email" : "alice@example.com"
}, {
  "name" : "Bob",
  "age" : 30,
  "email" : "bob@example.com"
}, {
  "name" : "Charlie",
  "age" : 35,
  "email" : "charlie@example.com"
}, {
  "name" : "John Smith",
  "age" : 35,
  "email" : "john.smith@example.com"
}, {
  "name" : "Jane Doe",
  "age" : 28,
  "email" : "jane.doe@example.com"
}, {
  "name" : "Bob Johnson",
  "age" : 42,
  "email" : "bob.johnson@example.com"
}, {
  "name" : "Alice Brown",
  "age" : 21,
  "email" : "alice.brown@example.com"
}, {
  "name" : "John Smith",
  "age" : 35,
  "email" : "john.smith@example.com"
}, {
  "name" : "Jane Doe",
  "age" : 28,
  "email" : "jane.doe@example.com"
}, {
  "name" : "Bob Johnson",
  "age" : 42,
  "email" : "bob.johnson@example.com"
}, {
  "name" : "Alice Brown",
  "age" : 21,
  "email" : "alice.brown@example.com"
}, {
  "name" : "Michael Davis",
  "age" : 56,
  "email" : "michael.davis@example.com"
}, {
  "name" : "Laura Gonzalez",
  "age" : 39,
  "email" : "laura.gonzalez@example.com"
}, {
  "name" : "David Lee",
  "age" : 44,
  "email" : "david.lee@example.com"
}, {
  "name" : "Samantha Martin",
  "age" : 31,
  "email" : "samantha.martin@example.com"
}, {
  "name" : "Mark Jones",
  "age" : 47,
  "email" : "mark.jones@example.com"
}, {
  "name" : "Emily Rodriguez",
  "age" : 26,
  "email" : "emily.rodriguez@example.com"
}, {
  "name" : "Eric Wilson",
  "age" : 38,
  "email" : "eric.wilson@example.com"
}, {
  "name" : "Grace Thomas",
  "age" : 29,
  "email" : "grace.thomas@example.com"
}, {
  "name" : "Jacob Young",
  "age" : 53,
  "email" : "jacob.young@example.com"
}, {
  "name" : "Olivia Hernandez",
  "age" : 22,
  "email" : "olivia.hernandez@example.com"
}, {
  "name" : "Patrick Wilson",
  "age" : 34,
  "email" : "patrick.wilson@example.com"
}, {
  "name" : "Isabella Ramirez",
  "age" : 27,
  "email" : "isabella.ramirez@example.com"
}, {
  "name" : "Christopher Johnson",
  "age" : 45,
  "email" : "christopher.johnson@example.com"
}, {
  "name" : "Sophia Thompson",
  "age" : 20,
  "email" : "sophia.thompson@example.com"
} ]